datasette/__init__.py
datasette/_version.py
datasette/app.py
datasette/cli.py
datasette/connectors.py
datasette/hookspecs.py
datasette/inspect.py
datasette/utils.py
datasette/version.py
datasette/static/app.css
datasette/static/codemirror-5.31.0-min.css
datasette/static/codemirror-5.31.0-sql.min.js
datasette/static/codemirror-5.31.0.js
datasette/templates/500.html
datasette/templates/_codemirror.html
datasette/templates/_codemirror_foot.html
datasette/templates/_description_source_license.html
datasette/templates/_rows_and_columns.html
datasette/templates/base.html
datasette/templates/database.html
datasette/templates/index.html
datasette/templates/query.html
datasette/templates/row.html
datasette/templates/show_json.html
datasette/templates/table.html
datasette/views/__init__.py
datasette/views/base.py
datasette/views/database.py
datasette/views/index.py
datasette/views/table.py
datasette_core-0.22.1.dist-info/METADATA
datasette_core-0.22.1.dist-info/RECORD
datasette_core-0.22.1.dist-info/WHEEL
datasette_core-0.22.1.dist-info/entry_points.txt
datasette_core-0.22.1.dist-info/top_level.txt
tests/__init__.py
tests/fixtures.py
tests/test_api.py
tests/test_docs.py
tests/test_html.py
tests/test_inspect.py
tests/test_utils.py
