Metadata-Version: 2.1
Name: datasette-core
Version: 0.22.1
Summary: An instant JSON API for your SQLite databases
Home-page: https://github.com/simonw/datasette
Author: Simon Willison
License: Apache License, Version 2.0
Platform: UNKNOWN
Classifier: Development Status :: 4 - Beta
Classifier: Intended Audience :: Developers
Classifier: Intended Audience :: Science/Research
Classifier: Intended Audience :: End Users/Desktop
Classifier: Topic :: Database
Classifier: License :: OSI Approved :: Apache Software License
Classifier: Programming Language :: Python :: 3.6
Classifier: Programming Language :: Python :: 3.5
Requires-Dist: click (==6.7)
Requires-Dist: click-default-group (==1.2)
Requires-Dist: Sanic (==0.7.0)
Requires-Dist: Jinja2 (==2.10)
Requires-Dist: hupper (==1.0)
Requires-Dist: pint (==0.8.1)
Requires-Dist: pluggy (<1.0,>=0.1.0)
